mcp_mermaid_image_gen/__init__.py
mcp_mermaid_image_gen/config.py
mcp_mermaid_image_gen/logging_config.py
mcp_mermaid_image_gen/server/__init__.py
mcp_mermaid_image_gen/server/app.py
mcp_mermaid_image_gen/tools/__init__.py
mcp_mermaid_image_gen/tools/mermaid_renderer.py
mcp_mermaid_image_gen-0.1.4.dist-info/licenses/LICENSE
mcp_mermaid_image_gen-0.1.4.dist-info/METADATA
mcp_mermaid_image_gen-0.1.4.dist-info/WHEEL
mcp_mermaid_image_gen-0.1.4.dist-info/entry_points.txt
mcp_mermaid_image_gen-0.1.4.dist-info/top_level.txt
mcp_mermaid_image_gen-0.1.4.dist-info/RECORD
