Metadata-Version: 2.4
Name: mcp_mermaid_image_gen
Version: 0.1.4
Summary: An MCP server that accepts mermaid code and generates diagrams as images.
Author-email: Tim Kitchens <timkitch@codingthefuture.ai>
License: MIT
Project-URL: Homepage, https://github.com/codingthefuturewithai/mcp_mermaid_image_gen
Project-URL: Repository, https://github.com/codingthefuturewithai/mcp_mermaid_image_gen
Requires-Python: <3.13,>=3.11
License-File: LICENSE
Requires-Dist: mcp>=1.0.0
Requires-Dist: mcp[cli]>=1.0.0
Requires-Dist: anyio>=4.5
Requires-Dist: starlette>=0.36.0
Requires-Dist: uvicorn>=0.27.0
Provides-Extra: dev
Requires-Dist: build; extra == "dev"
Requires-Dist: twine; extra == "dev"
Dynamic: license-file
